setup.py
distributions_sj/Binomialdistribution.py
distributions_sj/Gaussiandistribution.py
distributions_sj/Generaldistribution.py
distributions_sj/__init__.py
distributions_sj.egg-info/PKG-INFO
distributions_sj.egg-info/SOURCES.txt
distributions_sj.egg-info/dependency_links.txt
distributions_sj.egg-info/not-zip-safe
distributions_sj.egg-info/top_level.txt